histlabapi/__init__.py
histlabapi/histlabapi.py
histlabapi-0.1.1.dist-info/LICENSE
histlabapi-0.1.1.dist-info/METADATA
histlabapi-0.1.1.dist-info/WHEEL
histlabapi-0.1.1.dist-info/RECORD
