Metadata-Version: 2.1
Name: histlabapi
Version: 0.1.1
Summary: A Python library that makes it easy for users to access data from the Columbia History Lab's database by functioning as a wrapper around the History Lab's API.
Home-page: https://github.com/dgozal/histlabapi
License: MIT
Author: Derrick Gozal
Requires-Python: >=3.9,<4.0
Classifier: License :: OSI Approved :: MIT License
Classifier: Programming Language :: Python :: 3
Classifier: Programming Language :: Python :: 3.9
Classifier: Programming Language :: Python :: 3.10
Classifier: Programming Language :: Python :: 3.11
Requires-Dist: requests (>=2.31.0,<3.0.0)
Project-URL: Documentation, https://histlabapi.readthedocs.io
Project-URL: Repository, https://github.com/dgozal/histlabapi
